README.md
setup.py
onnconformity/__init__.py
onnconformity/conformity.py
onnconformity.egg-info/PKG-INFO
onnconformity.egg-info/SOURCES.txt
onnconformity.egg-info/dependency_links.txt
onnconformity.egg-info/top_level.txt