Metadata-Version: 2.1
Name: onnconformity
Version: 0.0.6
Summary: Convenience Python module for Cloud One Conformity
Home-page: https://onnconformity.oznetnerd.com
Author: Will Robinson
Author-email: will@oznetnerd.com
License: UNKNOWN
Platform: UNKNOWN
